{"ribD": "Gene", "nucA": "Gene", "ghrh": "Gene", "I": "Gene", "Zoerhiza.2_1_3": "Gene", "penicilliosis": "Disease", "finasteride": "AnatomicalTherapeuticChemicalCode", "cbpE": "Gene", "dhuI": "Gene", "nitrilotriacetamide": "MeSHSupplementaryConceptRecord", "wbbH": "Gene", "citrafungin A": "MeSHSupplementaryConceptRecord", "Toyonite": "MeSHSupplementaryConceptRecord", "tooeleite": "MeSHSupplementaryConceptRecord", "yggP": "Gene", "rpsNB": "Gene", "Hcm": "Gene", "cylindradine A": "MeSHSupplementaryConceptRecord", "adipamide": "MeSHSupplementaryConceptRecord", "dibenzepin": "Drug", "mucositis": "Disease", "bumetanide": "ChemicalCompound"}