{"priB": "INTJ", "of": "ADP", "left": "VERB", "and": "CCONJ", "SPOM_SPNCRNA.7355": "VERB", "second": "ADJ", "any": "DET", "except": "SCONJ", "ear": "INTJ", "A": "DET", "interacting": "VERB", "urocanate": "VERB", "essential": "ADJ", "Avian": "ADJ", "cytoplasmic": "ADJ", "fracture": "VERB", "around": "ADP", "internal": "ADJ", "prosthetic": "ADJ", "nipecotic": "ADJ", "primary": "ADJ", "Necrotizing": "VERB", "unspecified": "ADJ", "cortical": "ADJ", "Optic": "ADJ", "im:7140684": "INTJ", "O-(3-(trimethylammonium)phenyl)-1,3,2": "ADJ", "strain": "VERB", "dihydrolipoic": "ADJ", "myopathy": "ADJ", "Crushing": "VERB", "ether": "ADJ", "coli": "VERB", "contiguous": "ADJ", "yl)phenyl)-1H": "ADJ", "in": "ADP", "upper": "ADJ", "including": "VERB", "human": "ADJ", "obsolete": "ADJ", "prostatic": "ADJ", "linked": "VERB", "Retained": "VERB", "old": "ADJ", "magnetic": "ADJ", "foreign": "ADJ", "anterior": "ADJ", "Central": "ADJ", "hemorrhagic": "ADJ", "serine": "VERB", "rich": "ADJ", "ketohexanoic": "ADJ", "nonthermal": "ADJ", "medial": "ADJ", "lower": "ADJ", "mild": "ADJ", "pelovivens": "VERB", "by": "ADP", "acting": "VERB", "on": "ADP", "other": "ADJ", "assault": "VERB", "trafficking": "VERB", "nuclear": "ADJ", "binding": "ADJ", "SET": "ADJ", "new": "ADJ", "n": "CCONJ", "generalized": "ADJ", "common": "ADJ", "variable": "ADJ", "lncRNA": "ADJ", "niban": "ADJ", "2-(4-(4": "ADJ", "O": "ADJ", "asRNA": "ADJ", "anti": "ADJ", "-": "SYM", "inhibitor": "ADJ", "coagulant": "ADJ", "complex": "ADJ", "egaa": "ADV", "rhipicephali": "VERB", "Pool-7": "VERB", "rotundus": "VERB", "associated": "VERB", "Postcoital": "ADJ", "Synthetic": "ADJ", "alphabotrytidis": "VERB", "alexia": "ADJ", "uronate": "ADJ", "Inflammatory": "ADJ", "deoxo-4''-deoxy-3'-N": "ADJ", "mannotriose": "VERB", "muscular": "ADJ", "dystroglycanopathy": "ADJ", "Excessive": "ADJ", "at": "ADP", "aglycone": "VERB", "Idiopathic": "ADJ", "without": "ADP", "long": "ADJ", "with": "ADP", "achetakinin": "ADP", "rat": "CCONJ", "Miotic": "ADJ", "autosomal": "ADJ", "recessive": "ADJ", "oxo-4,5": "VERB", "to": "ADP", "the": "DET", "Other": "ADJ", "peroneal": "ADJ", "Malignant": "ADJ", "pleural": "ADJ", "cerevisiae": "VERB", "UNC-55": "ADJ", "gfus.3": "VERB", "sulfonyl)aminopropyl-1": "ADV", "oxyl)-4-((5,6,7,8": "ADJ", "ferrocenoyl": "ADJ", "strychnobrasiline": "ADJ", "olivacins": "VERB", "undigerum": "ADP", "pick": "VERB", "up": "ADP", "or": "CCONJ", "injured": "VERB", "specified": "ADJ", "diphenylcyclopropenone": "SCONJ", "/": "SYM", "monophosphate": "ADJ", "stachyonic": "ADJ", "*": "SYM", "piriprost": "VERB", "Guided": "VERB", "following": "VERB", "lelidair": "VERB", "degenerative": "ADJ", "eyelid": "ADJ", "periocular": "ADJ", "achlioniceoside": "ADP", "putative": "ADJ", "aggregans": "VERB", "diacetate": "VERB", "optic": "ADJ", "right": "ADJ", "zebrafish": "ADJ", "oblonga": "VERB", "alfa-2a": "AUX", "Visual": "ADJ", "ribosome": "ADJ", "soft": "ADJ", "csbX": "ADV", "acanthospermal": "ADJ", "superficial": "ADJ", "inducing": "VERB", "extracellular": "ADJ", "type": "VERB", "containing": "VERB", "papilloma": "ADJ", "prostaglandin": "ADJ", "main": "ADJ", "urinary": "ADJ", "fumarate": "ADJ", "suspensolide": "ADP", "methylene-1,3": "ADJ", "mweyba": "ADJ", "mitochondrial": "ADJ", "ribosomal": "ADJ", "poly": "ADJ", "diacetone": "ADJ", "from": "ADP", "thyrotoxic": "ADJ", "andinum": "ADJ", "oxo-1,2": "ADJ", "nucleolar": "ADJ", "like": "ADP", "oxo-2H": "ADP", "chromene-3": "ADJ", "ladinin": "ADJ", "propyl)morpholine": "SYM", "benzquinamide": "VERB", "6MKN_E.1": "ADV", "topical": "ADJ", "undetermined": "ADJ", "azidothymidine": "ADJ", "bromo-1,3": "ADJ", "benz(d": "ADJ", "e)isoquinoline-2(3H)-acetic": "ADJ", "parathyroid": "ADJ", "subfamily": "ADV", "I": "PRON", "member": "VERB", "Infectious": "ADJ", "pancreatic": "ADJ", "Personal": "ADJ", "circulatory": "ADJ", "After": "ADP", "Photobleaching": "VERB", "indol-1": "ADJ", "yl)butyric": "ADJ", "nicotianae": "ADJ", "multiple": "ADJ", "for": "ADP", "antenatal": "ADJ", "nuchal": "ADJ", "systemic": "ADJ", "glutamate": "ADJ", "Simian": "ADJ", "dominant": "ADJ", "nonsyndromic": "ADJ", "australis": "ADJ", "localized": "VERB", "arvivivens": "VERB", "methixene": "ADJ", "Azabicycloheptane": "ADJ", "carboxylic": "ADJ", "ilzat": "VERB", "Toll-6": "ADJ", "pyri": "VERB", "ciprofibrate": "VERB", "rheumatoid": "ADJ", "bicucullata": "ADJ", "Tracheobronchial": "ADJ", "originating": "VERB", "perinatal": "ADJ", "bis(5": "VERB", "methotrexate": "ADJ", "Ectopic": "ADJ", "perineal": "ADJ", "bilateral": "ADJ", "Takotsubo": "VERB", "isopropylphenylbutanal": "ADJ", "Unspecified": "ADJ", "physeal": "ADJ", " ": "SPACE", "Gemignani": "ADJ", "glycolicus": "VERB", "dimethyl-2H": "ADV", "kitalase": "VERB", "glucopyranosyluronoylglucopyranoside": "ADJ", "yl)thiophene-2": "ADJ", "benzopyrano(3,4": "ADJ", "SPOM_SPNCRNA.6697": "VERB", "difluoro-5,7": "ADJ", "bora-3a,4a": "VERB", "aspartic": "ADJ", "accidentally": "ADV", "enaminomycins": "VERB", "intellectual": "ADJ", "developmental": "ADJ", "pupillary": "ADJ", "related": "VERB", "Like": "ADJ", "ametantrone": "VERB", "HomB": "ADJ", "retinal": "ADJ", "pearsonii": "ADJ", "expressed": "VERB", "juvenile": "ADJ", "ankylosing": "VERB", "quinuclidinoyl)-1,2,3,4": "ADJ", "oxocholanoic": "ADJ"}