{"CENPM": "VERB", "RALGDS": "ADJ", "koko": "VERB", "lb": "ADP", "coagulant": "ADJ", "white": "ADJ", "strain": "VERB", "Crushing": "VERB", "of": "ADP", "human": "ADJ", "bcsB": "ADV", "polymaleinate": "VERB", "activating": "VERB", "yl)oxy)propanamide": "VERB", "tupichigenin": "ADJ", "vctD": "INTJ", "nicotinic": "ADJ", "/": "SYM", "Toxic": "ADJ", "accidental": "ADJ", "unintentional": "ADJ", "-": "SYM", "His": "PRON", "Post": "ADJ", "traumatic": "ADJ", "chronic": "ADJ", "responsive": "ADJ", "binding": "VERB", "pseudoglabrans": "VERB", "belcheri": "ADJ", "associated": "VERB", "threonine": "ADJ", "tousled": "VERB", "like": "ADP", "para": "ADJ", "with": "ADP", "rheumatoid": "ADJ", "unspecified": "ADJ", "desbromoleptophos": "ADV", "azido": "ADJ", "without": "ADP", "foreign": "ADJ", "metastatic": "ADJ", "to": "ADP", "the": "DET", "Other": "ADJ", "superficial": "ADJ", "stilbelliformis": "VERB", "dopachrome": "ADJ", "by": "ADP", "falling": "VERB", "on": "ADP", "other": "ADJ", "powered": "ADJ", "homo": "ADJ", "rich": "ADJ", "and": "CCONJ", "cerevisiae": "VERB", "distal": "ADJ", "interphalangeal": "ADJ", "left": "ADJ", "I": "PRON", "tactile": "ADP", "zebrafish": "ADJ", "gengar": "ADJ", "acetamidobenzoic": "ADJ", "glucosaminic": "ADJ", "l(1)N8": "VERB", "A": "DET", "Familial": "ADJ", "primary": "ADJ", "small": "ADJ", "nucleolar": "ADJ", "complex": "ADJ", "4-(4": "VERB", "yellow": "ADJ", "cerealis": "VERB", "s": "PART", "iodoisatin": "ADJ", "affecting": "VERB", "electrolyte": "ADJ", "D": "ADJ", "glucopyranosyl": "ADJ", "sclerotinin": "ADJ", "promoting": "VERB", "phenylisothiocyanate": "ADJ", "Reverse": "ADJ", "Rb(4.12)9Bnr": "INTJ", "Genetic": "ADJ", "malignant": "VERB", "en-24": "ADP", "acecarbromal": "ADJ", "microRNA": "ADV", "Chro.60300": "ADJ", "fallax": "VERB", "social": "ADJ", "emotional": "ADJ", "clcb": "VERB", "neonectrolide": "ADJ", "N,-diethylglycinate": "ADJ", "not": "PART", "elsewhere": "ADV", "classified": "VERB", "antibiotic": "ADJ", "benzoylleucyl": "ADJ", "containing": "VERB", "draining": "VERB", "multiple": "ADJ", "leukocyte": "ADJ", "right": "ADJ", "any": "DET", "except": "SCONJ", "ear": "ADP", "l(1)Q42": "AUX", "aggressive": "ADJ", "digital": "ADJ", "papillary": "ADJ", "lncRNA": "ADJ", ":": "SYM", "upper": "ADJ", "glutaric": "ADJ", "nifedipine": "ADJ", "tetrahydrofolate": "ADJ", "promontorii": "ADV", "ecdysone": "ADJ", "massiliensis": "VERB", "superior": "ADJ", "mesenteric": "ADJ", "dithiolan-4": "ADJ", "carboxylic": "ADJ", "secbutabarbital": "VERB", "nephrotic": "ADJ", "mitochondrial": "ADJ", "uptake": "ADJ", "atypical": "ADJ", "Minor": "ADJ", "pulmonary": "ADJ", "phenyl-4-(4": "ADJ", "sulfonatopropoxy)-1,4": "ADJ", "alt-1,4": "ADP", "diisocyano-1-(4": "ADJ", "methoxyphenyl)buta-1,3": "ADJ", "stearoyl-2": "ADJ", "glutaroyl": "ADJ", "chorioretinal": "ADJ", "BE": "AUX", "obsolete": "ADJ", "ciliary": "ADJ", "type": "VERB", "tnrIGAU": "ADP", "methyl-4-(O": "ADJ", "S-(2,4,5": "ADJ", "trimethoxy": "ADJ", "'": "VERB", "dioxo-7-(phenylethylamino)heptanohydroxamic": "ADJ", "melaeniza": "ADJ", "edoxaban": "ADJ", "n": "CCONJ", "glutamate": "ADJ", "tricladic": "ADJ", "hematogenous": "ADJ", "dihydroquinoline-3": "VERB", "morclofone": "VERB", "sulfobenzylethylaminophenyl)acetonitrile": "SYM", "branched": "VERB", "glycated": "VERB", "Heredofamilial": "ADJ", "methacrylate": "ADJ", "iminodiacetic": "ADJ", "first": "ADJ", "hexanesulfonic": "ADJ", "2-(2-(3-(4": "ADV", "chloro-3-(trifluoromethyl)phenyl)ureido)-4-(trifluoromethyl)phenoxy)-4,5": "VERB", "dichlorobenzenesulfonic": "ADJ", "centromere": "ADJ", "oxonaphthalen-1(2H)-ylidene)methylamino)acetate": "VERB", "furfural": "ADJ", "spinal": "ADJ", "muscular": "ADJ", "Unspecified": "ADJ", "soft": "ADJ", "related": "VERB", "use": "VERB", "toluenesulfonate": "ADJ", "rat": "CCONJ", "box": "VERB", "oralis": "VERB", "danielii": "VERB", "methionine": "ADJ", "fenamidone": "VERB", "EscU": "ADJ", "coli": "VERB", "cytochrome": "VERB", "phenyl-9,10": "ADJ", "monomethanesulfonate": "ADJ", "including": "VERB", "familial": "ADJ", "valyl": "ADJ", "prolyl": "ADJ", "due": "ADP", "underlying": "ADJ", "diabetic": "ADJ", "neuropathy": "ADJ", "epi-3,20": "ADJ", "Accelerated": "VERB", "Chinese": "ADJ", "phailmary": "ADJ", "glepidotin": "VERB", "interacting": "VERB", "seganserin": "VERB", "methylmalonic": "ADJ", "Recessive": "ADJ", "bipyridyl": "ADJ", "dinitro": "ADJ", "oxazolidine": "VERB", "superfamily": "ADV", "sulfoxide": "ADP", "tabescens": "VERB", "as": "ADP", "external": "ADJ", "metabolite": "VERB", "vertebral": "ADJ", "dilated": "VERB", "cardiomyopathy": "ADJ", "hypergonadotropic": "ADJ", "sgkB": "ADV", "ylazo": "ADJ", "benzene-1,3": "ADJ", "unilateral": "ADJ", "secondary": "ADJ", "chlorotic": "ADJ", "cantharidate": "VERB", "occidiofungin": "ADJ", "iodosulpride": "ADJ", "disseminated": "VERB", "intravascular": "ADJ", "third": "ADJ", "methoxycarbazole": "ADJ", "Phospholipases": "VERB", "cardiac": "ADJ", "dansylaziridine": "ADJ", "subfamily": "ADV", "mearnsii": "ADJ", "l(2)R": "ADJ", "kavain": "VERB", "at": "ADP", "dichlorodiphenylamine-2": "VERB", "nonbiological": "ADJ", "3-(5'-hydroxymethyl-2'-furyl)-1": "ADJ", "arecatemine": "VERB", "AM-7359": "INTJ", "venomous": "ADJ", "undetermined": "ADJ", "excess": "ADJ", "lacrimal": "ADJ", "uracil": "ADJ", "anterior": "ADJ", "component": "VERB", "Continuing": "VERB", "after": "ADP", "intrauterine": "ADJ", "or": "CCONJ", "more": "ADJ", "Early": "ADJ", "'s": "PART", "tuberculous": "ADJ", "urinary": "ADJ", "b)quinazolin-2": "ADP"}