{"dichlorobenzylidene)amino)-5,6": "ADJ", "dihydro-4H": "ADJ", "carbonitrile": "ADJ", "earlei": "VERB", "like": "INTJ", "Rb(10.17)9Mpl": "VERB", "vein": "ADJ", "dimethyl-4-(6-(methylthio)imidazo(1,2": "ADJ", "a)pyridine-2": "ADJ", "by": "ADP", "anterior": "ADJ", "pituitary": "ADJ", "adenohypophyseal": "ADJ", "human": "ADJ", "obsolete": "ADJ", "anaplastic": "ADJ", "of": "ADP", "entomophila": "VERB", "siebolside": "VERB", "A": "PRON", "tubular": "ADJ", "variant": "ADJ", "Idiopathic": "ADJ", "aseptic": "ADJ", "right": "ADJ", "banding": "VERB", "mosaic": "ADJ", "strain": "VERB", "yl)phenyl)-1H": "ADJ", "unspecified": "ADJ", "multiple": "ADJ", "and": "CCONJ", "sensorineural": "ADJ", "distinctive": "ADJ", "facial": "ADJ", "And": "CCONJ", "following": "VERB", "other": "ADJ", "cerebrovascular": "ADJ", "activating": "VERB", "sexual": "ADJ", "specific": "ADJ", "Unspecified": "ADJ", "bilateral": "ADJ", "oxo-1,1": "ADJ", "-": "SYM", "diphenyltetrahydrooxazolo(3,4": "ADJ", "a)pyrazine-7": "ADJ", "carboxylic": "ADJ", "cerevisiae": "VERB", "Other": "ADJ", "specified": "VERB", "pancreatic": "ADJ", "internal": "ADJ", "os": "ADP", "left": "VERB", "dehydrogenase": "VERB", "mediated": "VERB", "silencing": "VERB", "tetrakis(carbamoylmethyl)-1,4,7,10": "ADJ", "congenital": "ADJ", "scrotum": "VERB", "proJ": "ADP", "traumatic": "ADJ", "epacadostat": "VERB", "bullous": "ADJ", "folate": "ADJ", "anemias": "VERB", "zebrafish": "ADJ", "Intestinal": "ADJ", "as": "ADP", "to": "ADP", "partial": "ADJ", "versus": "ADP", "complete": "ADJ", "benign": "ADJ", "connective": "ADJ", "soft": "ADJ", "sulfonic": "ADJ", "third": "ADJ", "Releasing": "VERB", "wrinkled": "VERB", "inducing": "VERB", "myeloproliferative": "ADJ", "Pftf": "ADJ", "annuum": "VERB", "nigelladine": "ADJ", "first": "ADJ", "not": "PART", "including": "VERB", "nonthermal": "ADJ", "in": "ADP", "Fall": "VERB", "into": "ADP", "striking": "VERB", "agkisacutacin": "ADP", "bromoisovaleric": "ADJ", "associated": "VERB", "oxo-1,2": "ADJ", "with": "ADP", "External": "ADJ", "agrenecus": "ADJ", "fetal": "ADJ", "linked": "VERB", "n": "CCONJ", "butyl)phosphinic": "ADJ", "procyanidin": "VERB", "adrenal": "ADJ", "mntD": "INTJ", "dynorphin": "VERB", "Pathological": "ADJ", "elsewhere": "ADV", "classified": "VERB", "separans": "VERB", "provisional": "ADJ", "yl-1,5": "ADJ", "polydnavirus": "VERB", "foreign": "ADJ", "chlorine-3,15": "ADJ", "dioxy": "ADJ", "gibberellic": "ADJ", "predominantly": "ADV", "affecting": "VERB", "dehydroandrographolide": "VERB", "malignant": "ADJ", "tash": "VERB", "butyl": "ADJ", "N-4": "ADJ", "ethylbenzoyl": "ADJ", "N'-3,4": "ADJ", "amino-3-(4": "VERB", "reagent": "ADJ", "methyl-2-(1": "ADJ", "induced": "VERB", "interstitial": "ADJ", "microRNA": "ADJ", "ubiquinone": "ADJ", "superficial": "ADJ", "ectodermal": "ADJ", "rat": "CCONJ", "pulchellalactam": "VERB", "Containing": "VERB", "sinicus": "VERB", "ecotropic": "ADJ", "viral": "ADJ", "agricultural": "ADJ", "srfT": "ADJ", "lacrimal": "ADJ", "dimethylmalic": "ADJ", "nocardial": "ADJ", "Inocybe": "ADP", "subretipes": "VERB", "nervous": "ADJ", "prosthetic": "ADJ", "/": "SYM", "neonatal": "ADJ", "octanedioic": "ADJ", "Neonatal": "ADJ", "diphosphate": "ADJ", "nitratomethyl-1,2,3,4": "ADJ", "amide": "ADV", "Secondary": "ADJ", "associating": "VERB", "lygodiumsteroside": "INTJ", "aminoethyl": "ADJ", "phosphonic": "ADJ", "distal": "ADJ", "methoxyphenyl)naphtho(1,2": "ADJ", "ocular": "ADJ", "on": "ADP", "injured": "VERB", "or": "CCONJ", "wheeled": "VERB", "Circassian": "ADJ", "glutaminyl": "ADJ", "prolyl": "ADJ", "piericidin": "VERB", "Cystic": "ADJ", "posterior": "ADJ", "lateral": "ADJ", "nucleolar": "ADJ", "the": "DET", "Episodic": "ADJ", "intractable": "ADJ", "at": "ADP", "nitropropionic": "ADJ", "acetylbenzofuran": "ADJ", "cytochrome": "ADJ", "subfamily": "ADV", "triacetate": "VERB", "atrophic": "ADJ", "A(4": "CCONJ", "carbonyl)piperazine-2,3": "ADJ", "paralytic": "ADJ", "nontraumatic": "ADJ", "intracranial": "ADJ", "dominant": "ADJ", "ulnar": "ADJ", "chromosomal": "ADJ", "'s": "PART", "Rhodanobacter": "VERB", "thymidine": "ADJ", "methyladenine": "ADJ", "Like": "ADJ", "rich": "ADJ", "containing": "VERB", "Nodular": "ADJ", "corneal": "ADJ", "stills": "VERB", "opportunistic": "ADJ", "bacterial": "ADJ", "infectious": "ADJ", "herbal": "ADJ", "2S,4R)-4,5,7": "ADJ", "acetylglucopyranoside-7": "ADJ", "O": "ADJ", "dodecanediylbis(phosphonic": "ADJ", "without": "ADP", "intracondylar": "ADJ", "lower": "ADJ", "femur": "ADJ", "SPOM_SPNCRNA.3437": "PRON", "syringylbergenin": "ADJ", "methyl-4-(1": "ADJ", "methyl-4-(4": "ADJ", "reconstructed": "ADJ", "occlusive": "ADJ", "Usher": "ADJ", "flexile": "ADJ", "ynoic": "ADJ", "1-(5-(3": "ADJ", "pyrazolo(3,4": "ADJ", "except": "SCONJ", "transposase": "VERB", "hydrogeniphila": "VERB", "binding": "VERB", "small": "ADJ", "for": "ADP", "gestational": "ADJ", "less": "ADJ", "than": "ADP", "retinal": "ADJ", "vascular": "ADJ", "long": "ADJ", "non": "ADJ", "coding": "ADJ", "coli": "VERB", "phosphoenolpyruvate": "ADJ", "polysaccharide": "ADJ", "tympanic": "ADJ", "mental": "ADJ", "variable": "ADJ", "cytokine": "VERB", "due": "ADP", "being": "AUX", "washed": "VERB", "overboard": "ADV", "from": "ADP", "acetyl": "ADJ", "valyl": "ADJ", "antigen": "SCONJ", "Dilated": "ADJ", "methyl-8-(2": "ADJ", "methyl-1": "ADV", "naphthaleneheptanoic": "ADJ", "Intraoperative": "ADJ", "a": "DET", "complicating": "VERB", "phosphinomethylmalic": "ADJ", "affected": "VERB", "premature": "ADJ", "sequential": "ADJ", "osmanthi": "ADV", "stimulant": "ADJ", "Abnormal": "ADJ", "lytic": "ADJ", "schizophylloides": "VERB", "methyltransferase": "VERB", "siberiense": "ADJ", "diosgenin": "VERB", "O-(rhamnopyranosyl-1": "ADV", "minquartynoic": "ADJ", "deacetylfusidic": "ADJ", "constant": "ADJ", "complementing": "VERB", "ectonucleoside": "ADJ", "snoRNA": "ADJ", "conferring": "VERB", "hydroxy-6": "VERB", "magnum": "ADJ", "F(2t)-isoprostane": "ADJ", "kinase": "ADV", "delbrueckii": "ADJ", "taberi": "VERB", "nitrate": "ADJ", "YSK": "ADJ", "Displaced": "VERB", "oblique": "ADJ", "ulna": "ADJ", "drawn": "VERB", "trichoketide": "VERB", "salvianolic": "ADJ", "meninges": "VERB", "GTPase": "ADJ", "phenylaminomethyl": "ADJ", "eyelid": "ADJ", "neuropeptide": "ADP", "fracture": "VERB", "around": "ADP", "palmitic": "ADJ", "external": "ADJ", "zaleplon": "VERB", "secondary": "ADJ", "ubiquitin": "ADJ", "ligase": "VERB", "cerolens": "AUX", "atofluding": "VERB", "triacetic": "ADJ", "Z)-4-((7,8": "ADJ", "exo-1,3": "ADJ", "neoplastic": "ADJ", "fibula": "ADP", "stimulating": "VERB", "beta": "ADJ", "hypomyelinating": "VERB", "dilated": "VERB", "cardiomyopathy": "ADJ", "dahlii": "VERB"}