{"dppC": "Gene", "ansR": "Gene", "ccsa": "Gene", "indanidine": "MeSHSupplementaryConceptRecord", "Dgkz": "Gene", "trofosfamide": "Drug", "cereotagaloperoxide": "MeSHSupplementaryConceptRecord", "secobarbital": "Drug", "ycnB": "Gene", "rectal adenoma": "Disease", "bentiromide": "ChemicalCompound", "fs(2)BA37": "Gene", "tropapride": "MeSHSupplementaryConceptRecord", "uterine fibroid": "Disease", "sdsR": "Gene", "pcrG": "Gene", "cysNC": "Gene", "utrophin": "Gene", "aminopentamide": "MeSHSupplementaryConceptRecord", "trnAguu": "Gene", "resmetirom": "MeSHSupplementaryConceptRecord", "PTMB.160c": "Gene"}