{"by": "ADP", "adverse": "ADJ", "of": "ADP", "and": "CCONJ", "other": "ADJ", "repo": "INTJ", "bgm": "VERB", "sixth": "ADJ", "due": "ADP", "to": "ADP", "human": "ADJ", "ell": "INTJ", "'s": "PART", "asiohabitans": "VERB", "rhamnogalacturonan": "VERB", "nfkbiaa": "ADJ", "hisT": "ADV", "derived": "VERB", "monocyte": "ADJ", "chemotactic": "ADJ", "hydroxy-5": "ADJ", "octanoylbenzoic": "ADJ", "lncRNA": "ADJ", "Nal(1)-4": "ADJ", "polybromo": "ADJ", "mosaic": "ADJ", "Esthiorhiza.2_36_3": "PRON", "specified": "VERB", "dipicolinic": "ADJ", "lactic": "ADJ", "O": "ADJ", "carboxylic": "ADJ", "adrienneae": "ADV", "involving": "VERB", "obliterative": "VERB", "with": "ADP", "enoic": "ADJ", "acid-(2-(4": "VERB", "zebrafish": "ADJ", "PavA": "ADP", "toxic": "ADJ", "Multiple": "ADJ", "right": "ADJ", "hpcR": "ADJ", "n": "CCONJ", "trichlorosilane": "ADJ", "aminobenzoyl": "ADJ", "CoA": "ADJ", "long": "ADJ", "non": "ADJ", "-": "ADJ", "coding": "ADJ", "sepharose": "ADJ", "4B": "ADJ", "Open": "ADJ", "unspecified": "ADJ", "external": "ADJ", "genital": "ADJ", "male": "ADJ", "Satisfactory": "ADJ", "anal": "ADJ", "but": "CCONJ", "lacking": "VERB", "shbA": "INTJ", "used": "VERB", "in": "ADP", "cardiac": "ADJ", "Bipolar": "ADJ", "current": "ADJ", "manic": "ADJ", "without": "ADP", "psychotic": "ADJ", "mild": "ADJ", "hydroxy-6,7,8": "ADJ", "cervical": "ADJ", "xenobiotic": "ADJ", "A": "DET", "direct": "ADJ", "polypeptide": "ADP", "physeal": "ADJ", "left": "VERB", "microRNA": "ADV", "veratric": "ADJ", "chloroloma": "VERB", "lathyri": "ADP", "centrosomal": "ADJ", "like": "ADP", "pyrrolidone": "VERB", "acrylic": "ADJ", "aitchisonide": "ADJ", "Other": "ADJ", "the": "DET", "neural": "ADJ", "benzylidene": "ADJ", "canescens": "VERB", "mcfG": "ADJ", "military": "ADJ", "Posterior": "ADJ", "subcapsular": "ADJ", "polar": "ADJ", "related": "VERB", "Progressive": "ADJ", "binding": "VERB", "secreted": "VERB", "frizzled": "VERB", "CKA-1306": "ADJ", "SPOM_SPNCRNA.5994": "INTJ", "injured": "VERB", "between": "ADP", "pick": "VERB", "up": "ADP", "or": "CCONJ", "recurrent": "VERB", "vertebral": "ADJ", "sacral": "ADJ", "/": "SYM", "containing": "VERB", "trafficking": "VERB", "acetic": "ADJ", "second": "ADJ", "shade": "VERB", "Atrial": "ADJ", "septal": "ADJ", "cinnamic": "ADJ", "acetal": "ADJ", "degeliana": "VERB", "Crushing": "VERB", "nondisplaced": "ADJ", "first": "ADJ", "aspafilioside": "ADJ", "arpH": "ADJ", "butyl": "VERB", "Simple": "ADJ", "chronic": "ADJ", "tufted": "VERB", "marmoset": "ADJ", "simian": "ADJ", "foamy": "ADJ", "Hodgkin": "ADJ", "Conductive": "ADJ", "unilateral": "ADJ", "unrestricted": "ADJ", "on": "ADP", "contralateral": "ADJ", "spatial": "ADJ", "following": "VERB", "nontraumatic": "ADJ", "intracerebral": "ADJ", "glutamate": "ADJ", "anterior": "ADJ", "eukaryotic": "ADJ", "strain": "VERB", "monophosphate": "ADJ", "impA": "ADJ", "hydroxy": "ADJ", "fomitopinic": "ADJ", "lower": "ADJ", "dideoxyglucose": "ADJ", "im:7145733": "ADP", "Personal": "ADJ", "malignant": "ADJ", "benzazocine-1": "ADJ", "aragusterol": "VERB", "I": "PRON", "trimethylphenyl)thioethyl)-4": "VERB", "lysyl": "ADJ", "Transitory": "ADJ", "newborn": "ADJ", "prkab": "ADJ", "3,5,6": "ADJ", "trimethylpyrazinecarboxylic": "ADJ", "dicarboxylate": "ADJ", "acetyl": "ADJ", "beta": "ADJ", "noladin": "ADJ", "ether": "ADJ", "ethyl": "ADJ", "pyrazol-1": "ADV", "Respiratory": "ADJ", "whether": "SCONJ", "manganese": "ADJ", "tyrosyl": "ADJ", "aminoisobutyric": "ADJ", "benzylphosphonic": "VERB", "nephritic": "ADJ", "morphologic": "ADJ", "congmuyenoside": "ADJ", "gated": "VERB", "interacting": "VERB", "SPOM_SPNCRNA.6529": "ADV", "blue": "ADJ", "pantripin": "ADJ", "polymyxin": "ADJ", "sisi": "VERB", "interveinal": "ADJ", "Pro(1)-4": "VERB", "conorii": "VERB", "maleimidohexanoic": "ADJ", "Inocybe": "SCONJ", "upper": "ADJ", "tris(N": "PRON", "soli": "ADJ", "obruta": "ADV", "diethyl": "ADJ", "neuropeptide": "ADP", "diphenyl": "VERB", "ducreyi": "VERB", "asRNA": "ADJ", "albizoside": "ADJ", "orbital": "ADJ", "not": "PART", "as": "SCONJ", "traumatic": "ADJ", "hypertrophic": "ADJ", "cardiomyopathy": "ADJ", "silencing": "VERB", "marasmioides": "VERB", "Unspecified": "ADJ", "eyelid": "ADJ", "dibromoquinone": "ADJ", "activating": "VERB", "methylene": "ADJ", "chalone": "ADJ", "hydroxide": "ADV", "discipulorum": "VERB", "insolens": "VERB", "posterior": "ADJ", "ilioischial": "ADJ", "duplicated": "VERB", "transcript": "VERB", "ethoxy-1,4": "ADJ", "ium-1,2": "ADJ", "diolate": "ADJ", "ureohydrolase": "ADJ", "azido-2'-deoxyinosine": "ADJ", "acquired": "VERB", "hydroxytormentic": "ADJ", "balcanica": "ADV", "l(1)adl8": "CCONJ", "And": "CCONJ", "complex": "ADJ", "chlorin": "VERB", "glycines": "VERB", "associated": "VERB", "acetate": "VERB", "filaminast": "VERB", "affected": "VERB", "O-(beta": "ADJ", "obsolete": "ADJ", "nodular": "ADJ", "inguinal": "ADJ", "Retinal": "ADJ", "giant": "ADJ", "retinal": "ADJ", "peroneal": "ADJ", "at": "ADP", "polycystic": "ADJ", "ovary": "ADJ", "subcutaneous": "ADJ", "borealis": "PART", "mitochondrial": "ADJ", "ribosomal": "ADJ", "acetylmuramyl": "ADP", "displaced": "ADJ", "third": "ADJ", "penta": "ADJ", "oxolanost-9(11)-ene-24,25": "ADJ", "alpha": "ADJ", "dihydroganoderate": "ADJ", "lumbar": "ADJ", "nitro-(4)peristylane-1,5": "ADJ", "With": "ADP", "secondary": "ADJ", "fasciculic": "ADJ", "subfamily": "ADV", "glycol": "ADJ", "recombinant": "ADJ", "abicolens": "VERB", "pituitary": "ADJ", "adenylate": "ADJ", "v": "ADP", "sp": "ADP", "mouse": "VERB", "narcissiflorine": "ADJ", "oxo-7": "ADJ", "xanthone-2": "ADJ", "amino-2-(4": "ADJ", "chlorophenyl)ethanesulfonic": "ADJ", "frozen": "VERB", "regulated": "VERB", "Mn(III)Mn(IV)(2": "ADJ", "ginsengisoli": "VERB", "valyl": "ADJ", "prolyl": "ADJ", "aspartic": "ADJ", "perineal": "ADJ", "coiled": "VERB", "rufofusca": "VERB", "cerevisiae": "VERB", "nonvenomous": "ADJ", "Mycotic": "ADJ", "corneal": "ADJ", "diphosphate": "ADJ", "primary": "ADJ", "autosomal": "ADJ", "recessive": "ADJ", "phenthoate": "ADJ", "l(1)K6": "ADJ", "Non": "ADJ", "pressure": "ADJ", "hydroxyphenylacetic": "ADJ", "5B": "ADJ", "paneolic": "ADJ", "induced": "VERB", "dysidotronic": "ADJ", "phosphate": "ADJ", "phenylhexanoyl": "ADJ", "yl)-2-'-methylpropanamide": "ADV", "hydroxybenzylidene-2,3": "ADJ", "iodo-2'-fluoroarabinosyluridine": "ADJ", "wild": "ADJ"}