{"potA": "Gene", "pstk": "Gene", "pinacolyl dimethylphosphinate": "MeSHSupplementaryConceptRecord", "crtB": "Gene", "niaP": "Gene", "euphornin": "MeSHSupplementaryConceptRecord", "lactocepin": "MeSHSupplementaryConceptRecord", "yjfB": "Gene", "tadehaginosin": "MeSHSupplementaryConceptRecord", "hydropiperoside": "MeSHSupplementaryConceptRecord", "Flushing": "Disease", "membranacin": "MeSHSupplementaryConceptRecord", "mannozym": "MeSHSupplementaryConceptRecord", "l(3)M256": "Gene", "thi": "Gene", "apiopaeonoside": "MeSHSupplementaryConceptRecord", "cleistophenolide": "MeSHSupplementaryConceptRecord", "isorosthin A": "MeSHSupplementaryConceptRecord", "trichocyclodipeptide A": "MeSHSupplementaryConceptRecord", "dioxosarcoguaiacol": "MeSHSupplementaryConceptRecord", "etanercept": "AnatomicalTherapeuticChemicalCode", "l(1)adl2": "Gene", "dinosterol": "MeSHSupplementaryConceptRecord", "miharamycin A": "MeSHSupplementaryConceptRecord", "manzamine A": "MeSHSupplementaryConceptRecord"}