{"engB": "ADV", "Axn": "VERB", "myopathy": "ADJ", "m": "ADV", "methoxypoly(ethylene)glycol": "ADJ", "polylysyl": "ADJ", "zebrafish": "ADJ", "resendei": "VERB", "coli": "VERB", "cerebral": "ADJ", "-": "SYM", "linked": "VERB", "poly-5": "ADJ", "mercuriuridylic": "ADJ", "yitZ": "ADJ", "polyneuropathy": "ADJ", "with": "ADP", "rheumatoid": "ADJ", "of": "ADP", "unspecified": "ADJ", "claspin": "ADJ", "complex": "ADJ", "A": "DET", "right": "ADJ", "for": "ADP", "internal": "ADJ", "yknV": "INTJ", "without": "ADP", "gdnD": "VERB", "strain": "VERB", "reptimed": "VERB", "herbal": "ADJ", "eyre": "VERB", "pre": "ADJ", "mRNA": "ADJ", "beijerinckii": "VERB", "lncRNA": "ADJ", "fancc": "VERB", "conduritol": "ADJ", "involving": "VERB", "due": "ADJ", "to": "ADP", "other": "ADJ", "civilian": "ADJ", "Osseous": "ADJ", "neural": "ADJ", "variable": "ADJ", "non": "ADJ", "functional": "ADJ", "binding": "VERB", "subfamily": "ADV", "agardhii": "VERB", "Korean": "ADJ", "methylbenzhydryloxyacetic": "ADJ", "enzyme": "PRON", "second": "ADJ", "left": "VERB", "phosphorylated": "VERB", "high": "ADJ", "Anhydrides": "VERB", "chlM": "ADP", "induced": "VERB", "persisting": "VERB", "amnestic": "ADJ", "respiratory": "ADJ", "lower": "ADJ", "eyelid": "ADJ", "and": "CCONJ", "periocular": "ADJ", "Conus": "ADJ", "fs(1)de14": "ADJ", "otamixaban": "ADJ", "keratopathy": "ADJ", "Multiple": "ADJ", "hexadecyl-2": "ADJ", "enoic": "ADJ", "or": "CCONJ", "alighting": "VERB", "a": "DET", "injured": "VERB", "in": "ADP", "up": "ADP", "ookinete": "ADJ", "transporting": "VERB", "gastric": "ADJ", "like": "ADJ", "traW": "DET", "plectaniaxanthin": "ADP", "frostbite": "ADJ", "ear": "VERB", "anti": "ADJ", "inhibitor": "ADJ", "Halolactibacillus": "ADJ", "And": "CCONJ", "Other": "ADJ", "psychoactive": "ADJ", "Bilateral": "ADJ", "femoral": "ADJ", "not": "PART", "specified": "VERB", "as": "ADP", "recurrent": "ADJ", "Skeletal": "ADJ", "Inocybe": "ADV", "I": "PRON", "Anatomical": "ADJ", "narrow": "ADJ", "Malignant": "ADJ", "overlapping": "VERB", "aggregans": "VERB", "ZK": "DET", "at": "ADP", "cerevisiae": "VERB", "yfeJ": "INTJ", "human": "ADJ", "HEME": "ADJ", "Major": "ADJ", "acetylneuraminic": "ADJ", "di": "ADJ", "As": "ADP", "forward": "ADV", "trafficking": "VERB", "dehydroxycolubrinic": "ADJ", "drum": "VERB", "phosphate": "VERB", "Indian": "ADJ", "LacY": "ADJ", "viscata": "VERB", "lactostatin": "ADJ", "Inferior": "ADJ", "acromioclavicular": "ADJ", "joint": "ADJ", "dickinsii": "ADJ", "yncC": "INTJ", "autosomal": "ADJ", "recessive": "ADJ", "muscular": "ADJ", "elsewhere": "ADV", "classified": "VERB", "7S": "ADJ", "obsolete": "ADJ", "syndromic": "ADJ", "chidiebere": "VERB", "jinqing": "VERB", "cellular": "ADJ", "saliphilus": "CCONJ", "megaloblastic": "ADJ", "nitro-2-(2": "ADJ", "benzopyran-8": "ADJ", "acetic": "ADJ", "n": "CCONJ", "propylcholanoic": "ADJ", "methoxyethyl)-4": "VERB", "methyl-1,3": "ADJ", "isocyanurate": "ADJ", "fib": "ADJ", "superfamily": "ADV", "played": "VERB", "individually": "ADV", "rhamnosyl-1": "ADJ", "stobadine": "VERB", "Inbred": "ADJ", "fluoronicotinamide": "ADV", "brasilense": "VERB", "nontraffic": "ADJ", "'": "PART", "drewsii": "ADJ", "oxobutanoic": "ADJ", "hzg": "ADJ", "fusiforme": "ADJ", "polymyxin": "ADJ", "Paenibacillus": "ADP", "sacric": "ADJ", "familial": "ADJ", "tetrahydro-4": "ADJ", "viral": "ADJ", "CoA": "ADJ", "dynorphin": "VERB", "prolyl": "ADJ", "phenylalanyl)-O": "ADJ", "private": "ADJ", "public": "ADJ", "the": "DET", "external": "ADJ", "torrendii": "VERB", "tyrosyl": "ADJ", "arginyl": "ADJ", "benz(a)anthracene-3,4": "ADJ", "viridula": "VERB", "chloro-3-(4": "ADJ", "spiral": "ADJ", "significant": "ADJ", "superficial": "ADJ", "secondary": "ADJ", "3,3'-5,5'-tetra": "ADJ", "containing": "VERB", "RTKNA": "VERB", "radial": "ADJ", "associated": "VERB", "/": "SYM", "Sexual": "ADJ", "known": "VERB", "physiological": "ADJ", "Idiopathic": "ADJ", "inflammatory": "ADJ", "Mixed": "ADJ", "Ovarian": "ADJ", "mastadenovirus": "VERB", "rufoferruginea": "VERB", "nuclear": "ADJ", "interacting": "VERB", "SPOM_SPNCRNA.6162": "INTJ", "chlorotic": "ADJ", "mosaic": "ADJ", "isopropyl-5H": "ADJ", "shrew": "VERB", "MYBD": "ADJ", "oxo-4,5": "VERB", "dihydropyrazol-1": "ADJ", "yl)benzoic": "ADJ", "albicans": "VERB", "yl)amino)methyl)phosphonate": "ADJ", "bijugata": "VERB", "tetracaine": "ADJ", "vaginalis": "ADJ", "atrioventricular": "ADJ", "multiple": "ADJ", "foot": "VERB", "N'-dibenzyl-1,10": "ADJ", "deltorphin": "VERB", "gestational": "ADJ", "ovarian": "ADJ", "N-(4": "ADV", "nitrobenzoyl)-N',N'-bis(morpholino)phosphoric": "ADJ", "Transverse": "VERB", "vaginal": "ADJ", "capucinoides": "VERB", "nigricans": "VERB", "cramps": "VERB", "acral": "ADJ", "Familial": "ADJ", "cyclic": "ADJ", "spiro(indan-2,2'-pyrrolidine": "ADJ", "hydroxy-5": "ADJ", "malignant": "ADJ", "into": "ADV", "filled": "VERB", "mechanical": "ADJ", "arterial": "ADJ", "Personal": "ADJ", "prostatic": "ADJ", "anabolic": "ADJ", "SPOM_SPNCRNA.857": "ADJ", "isopropyl-5-(1": "ADJ", "tripartite": "ADJ", "cataplexy": "ADJ", "PNMA": "ADJ", "trnR(acg)4": "ADP", "heavy": "ADJ", "first": "ADJ", "sulfobromophthalein": "ADJ", "glutathione": "ADJ", "free": "ADJ", "radical": "ADJ", "Cortical": "ADJ", "limivivens": "VERB", "thiocarbonylsulfenylamino)ethyl)benzenesulfonamide": "ADP", "Vulvovaginal": "ADJ", "microRNA": "ADJ", "methoxyfumaroyl)-2,3": "ADJ", "cervical": "ADJ", "spinal": "ADJ", "ylamino)propyl)-N'-(4-(1,2,3,4": "ADJ", "Nle(17)-neurotensin(6": "ADJ", "by": "ADP", "intentional": "ADJ", "rat": "CCONJ", "Cervical": "ADJ", "radiculopathy": "ADJ", " ": "SPACE", "bushy": "ADJ", "alphasatellite": "PRON", "IN": "ADP", "appetite": "ADJ", "antibiotic": "ADJ", "cytochrome": "VERB", "long": "ADJ", "upper": "ADJ", "p": "ADP", "specific": "ADJ", "propenyl)hydrazo)-6": "ADJ", "carbamate": "ADJ", "nocardiosis": "VERB", "primary": "ADJ", "ether": "INTJ", "wiebeae": "VERB", "urea": "ADJ", "methoxydihydrochelerythrine": "ADJ", "indacaterol": "VERB"}