{"mqnE": "Gene", "nocta": "Gene", "triethynylphosphine": "MeSHSupplementaryConceptRecord", "acpK": "Gene", "secoheliospholane A": "MeSHSupplementaryConceptRecord", "tfb": "Gene", "yfiN": "Gene", "ngf": "Gene", "yhiD": "Gene", "yciT": "Gene", "Zoerhiza.2_15_2": "Gene", "Chro.40409": "Gene", "azelastine": "MeSHSupplementaryConceptRecord", "gxcI": "Gene", "tolbutamide": "ChemicalCompound", "etilevodopa": "MeSHSupplementaryConceptRecord", "sarmentamide A": "MeSHSupplementaryConceptRecord", "piroheptine": "MeSHSupplementaryConceptRecord", "zedoarol": "MeSHSupplementaryConceptRecord"}